whocan/__init__.py
whocan/_environment.py
whocan/_errors.py
whocan/_policies.py
whocan/_policy_sets.py
whocan-0.4.1.dist-info/METADATA
whocan-0.4.1.dist-info/WHEEL
whocan-0.4.1.dist-info/RECORD
