Metadata-Version: 2.1
Name: whocan
Version: 0.4.1
Summary: Library for defining and determining access.
Home-page: https://gitlab.com/kjschiroo/whocan
License: MIT
Author: Kevin Schiroo
Author-email: kjschiroo@gmail.com
Requires-Python: >=3.8,<4.0
Classifier: License :: OSI Approved :: MIT License
Classifier: Programming Language :: Python :: 3
Classifier: Programming Language :: Python :: 3.8
Classifier: Programming Language :: Python :: 3.9
Classifier: Programming Language :: Python :: 3.10
Classifier: Programming Language :: Python :: 3.11
Requires-Dist: PyYAML (>=6.0,<7.0)
Project-URL: Repository, https://gitlab.com/kjschiroo/whocan
